tdd_monitor/__init__.py
tdd_monitor/src/__init__.py
tdd_monitor/src/main.py
tdd_monitor/src/chore/__init__.py
tdd_monitor/src/chore/args_parse.py
tdd_monitor/src/chore/monitor.py
tdd_monitor/src/chore/signal_handler.py
tdd_monitor/src/chore/trigger_test.py
tdd_monitor/src/errors/__init__.py
tdd_monitor/src/errors/args_error.py
tdd_monitor/src/file_handling/__init__.py
tdd_monitor/src/file_handling/collect_test_files.py
tdd_monitor/src/file_handling/compare_files.py
tdd_monitor/src/file_handling/create_file.py
tdd_monitor/src/file_handling/get_file_name.py
tdd_monitor/src/file_handling/read_doc.py
tdd_monitor/src/templates/__init__.py
tdd_monitor/src/templates/init_test.py
tdd_monitor/src/templates/welcome.txt
tdd_monitor/tests/test_bad_usage.py
tdd_monitor-0.0.2b1.dist-info/LICENSE
tdd_monitor-0.0.2b1.dist-info/METADATA
tdd_monitor-0.0.2b1.dist-info/WHEEL
tdd_monitor-0.0.2b1.dist-info/entry_points.txt
tdd_monitor-0.0.2b1.dist-info/top_level.txt
tdd_monitor-0.0.2b1.dist-info/RECORD
