Metadata-Version: 2.1
Name: tdd-monitor
Version: 0.0.2b1
Summary: Simple script to automate running tests on files changes.Simplify test driven design
Home-page: https://github.com/FaelCaporali/tdd-pmon
Author: Fael Caporali
Author-email: faelcaporalidev@gmail.com
License: UNKNOWN
Platform: UNKNOWN
Classifier: Development Status :: 1 - Planning
Classifier: Intended Audience :: Developers
Classifier: License :: OSI Approved :: GNU General Public License (GPL)
Classifier: Programming Language :: Python
Classifier: Topic :: Software Development :: Libraries
License-File: LICENSE
Requires-Dist: pytest
Requires-Dist: pytest-xdist
